Aula Prática 6/Contador_sinc_0_15_pos/Cs015p.v
module Cs015p(PR, CLR, Q, clk);
    input PR, CLR, clk;
    output reg [3:0]Q;

    always @(posedge clk) begin
        if (PR == 1 & CLR == 0)
            Q = 4'b0000;
        else if (PR == 0 & CLR == 1)
            Q = 4'b1111;
        else if (PR == 0 & CLR == 0)
            Q = 4'bXXXX;
        else
            Q = Q + 1;
    end
endmodule

Aula Prática 6/Contador_sinc_0_15_pos/Cs015p_tb.v
`timescale 1ns/1ns
`include "Cs015p.v"

module Cs015p_tb;

    wire [3:0]Q;
    reg clk, PR, CLR;
    Cs015p uut(PR, CLR, Q, clk);

    initial begin
        $dumpfile("Cs015p.vcd");
        $dumpvars(0, Cs015p_tb);

        PR = 1; CLR = 0; #20;
        PR = 1; CLR = 1; #320;

        $display("Teste completo");
        $finish;
    end

    initial begin
        clk = 0;
        forever #10 clk = ~clk;
    end

endmodule

Aula Prática 6/Contador_sinc_0_15_pos/Cs015p.vcd
$date
	Fri Oct 25 09:11:01 2024
$end
$version
	Icarus Verilog
$end
$timescale
	1ns
$end
$scope module Cs015p_tb $end
$var wire 4 ! Q [3:0] $end
$var reg 1 " CLR $end
$var reg 1 # PR $end
$var reg 1 $ clk $end
$scope module uut $end
$var wire 1 " CLR $end
$var wire 1 # PR $end
$var wire 1 $ clk $end
$var reg 4 % Q [3:0] $end
$upscope $end
$upscope $end
$enddefinitions $end
$comment Show the parameter values. $end
$dumpall
$end
#0
$dumpvars
bx %
0$
1#
0"
bx !
$end
#10
b0 !
b0 %
1$
#20
0$
1"
#30
b1 !
b1 %
1$
#40
0$
#50
b10 !
b10 %
1$
#60
0$
#70
b11 !
b11 %
1$
#80
0$
#90
b100 !
b100 %
1$
#100
0$
#110
b101 !
b101 %
1$
#120
0$
#130
b110 !
b110 %
1$
#140
0$
#150
b111 !
b111 %
1$
#160
0$
#170
b1000 !
b1000 %
1$
#180
0$
#190
b1001 !
b1001 %
1$
#200
0$
#210
b1010 !
b1010 %
1$
#220
0$
#230
b1011 !
b1011 %
1$
#240
0$
#250
b1100 !
b1100 %
1$
#260
0$
#270
b1101 !
b1101 %
1$
#280
0$
#290
b1110 !
b1110 %
1$
#300
0$
#310
b1111 !
b1111 %
1$
#320
0$
#330
b0 !
b0 %
1$
