Aula Prática 5/FF_JK/FF_JK.v
module FF_JK(J, K, PR, CLR, Q, clk);
    input J, K, PR, CLR, clk;
    output reg Q;
    
    always @(posedge clk) begin
        if (PR == 0 & CLR == 1)
            Q = 1;
        else if (PR == 1 & CLR == 0)
            Q = 0;
        else if (PR == 0 & CLR == 0)
            Q = 1'bX;
        else case ({J, K})
            default:Q = Q;
            2'b01:Q = 0;
            2'b10:Q = 1;
            2'b11:Q = ~Q;
        endcase
    end
endmodule

Aula Prática 5/FF_JK/FF_JK_tb.v
`timescale 1ns/1ns
`include "FF_JK.v"

module FF_JK_tb;

    reg J, K, PR, CLR, clk;
    wire Q;
    FF_JK uut(J, K, PR, CLR, Q, clk);

    initial begin
        $dumpfile ("FF_JK.vcd");
        $dumpvars (1);

        PR = 1; CLR = 0; #20;
        PR = 1; CLR = 1; J = 0; K = 0; #20;
        J = 0; K = 1; #20;
        J = 1; K = 0; #20;
        J = 1; K = 1; #20;
        $finish;
    end

    initial begin
        clk = 0;
        forever #10 clk = ~ clk ;
    end
endmodule

Aula Prática 5/FF_JK/FF_JK.vcd
$date
	Fri Oct 04 08:47:26 2024
$end
$version
	Icarus Verilog
$end
$timescale
	1ns
$end
$scope module FF_JK_tb $end
$var wire 1 ! Q $end
$var reg 1 " CLR $end
$var reg 1 # J $end
$var reg 1 $ K $end
$var reg 1 % PR $end
$var reg 1 & clk $end
$upscope $end
$enddefinitions $end
$comment Show the parameter values. $end
$dumpall
$end
#0
$dumpvars
0&
1%
x$
x#
0"
x!
$end
#10
0!
1&
#20
0&
0$
0#
1"
#30
1&
#40
0&
1$
#50
1&
#60
0&
0$
1#
#70
1!
1&
#80
0&
1$
#90
0!
1&
