Aula Prática 6/Contador_assic_4crescb/FF_JK.v
module FF_JK(J, K, PR, CLR, Q, clk);
    input J, K, PR, CLR, clk;
    output reg Q;
    
    always @(negedge clk) begin
        if (PR == 0 & CLR == 1)
            Q = 1;
        else if (PR == 1 & CLR == 0)
            Q = 0;
        else if (PR == 0 & CLR == 0)
            Q = 1'bX;
        else case ({J, K})
            default:Q = Q;
            2'b01:Q = 0;
            2'b10:Q = 1;
            2'b11:Q = ~Q;
        endcase
    end
endmodule

Aula Prática 6/Contador_assic_4crescb/Ca4b.v
`include "FF_JK.v"

module Ca4b(T, PR, CLR, Q, clk);
    output reg [3:0]Q;
    input T, PR, CLR, clk;

    FF_JK uut1(T, T, PR, CLR, Q[0], clk);
    FF_JK uut2(T, T, PR, CLR, Q[1], Q[0]);
    FF_JK uut3(T, T, PR, CLR, Q[2], Q[1]);
    FF_JK uut4(T, T, PR, CLR, Q[3], Q[2]);
endmodule

Aula Prática 6/Contador_assic_4crescb/Ca4b_tb.v
`timescale 1ns/1ns
`include "Ca4b.v"

module Ca4b_tb;

    reg T;
    wire [3:0]Q;
    reg PR, CLR;
    reg clk;
    Ca4b uut(T, PR, CLR, Q, clk);

    initial begin
        $dumpfile("Ca4b.vcd");
        $dumpvars(0, Ca4b_tb);

        PR = 1; CLR = 0; T = 1; #20;
        PR = 1; CLR = 1; #300;

        $display("Teste completo");
        $finish;
    end

    initial begin
        clk = 0;
        forever #10 clk = ~clk;
    end

endmodule

Aula Prática 6/Contador_assic_4crescb/Ca4b.vcd
$date
	Fri Oct 25 08:38:35 2024
$end
$version
	Icarus Verilog
$end
$timescale
	1ns
$end
$scope module Ca4b_tb $end
$var wire 4 ! Q [3:0] $end
$var reg 1 " CLR $end
$var reg 1 # PR $end
$var reg 1 $ T $end
$var reg 1 % clk $end
$scope module uut $end
$var wire 1 " CLR $end
$var wire 1 # PR $end
$var wire 1 $ T $end
$var wire 1 % clk $end
$var wire 4 & Q [3:0] $end
$scope module uut1 $end
$var wire 1 " CLR $end
$var wire 1 $ J $end
$var wire 1 $ K $end
$var wire 1 # PR $end
$var wire 1 % clk $end
$var reg 1 ' Q $end
$upscope $end
$scope module uut2 $end
$var wire 1 " CLR $end
$var wire 1 $ J $end
$var wire 1 $ K $end
$var wire 1 # PR $end
$var wire 1 ( clk $end
$var reg 1 ) Q $end
$upscope $end
$scope module uut3 $end
$var wire 1 " CLR $end
$var wire 1 $ J $end
$var wire 1 $ K $end
$var wire 1 # PR $end
$var wire 1 * clk $end
$var reg 1 + Q $end
$upscope $end
$scope module uut4 $end
$var wire 1 " CLR $end
$var wire 1 $ J $end
$var wire 1 $ K $end
$var wire 1 # PR $end
$var wire 1 , clk $end
$var reg 1 - Q $end
$upscope $end
$upscope $end
$upscope $end
$enddefinitions $end
$comment Show the parameter values. $end
$dumpall
$end
#0
$dumpvars
0-
0,
0+
0*
0)
0(
0'
b0 &
0%
1$
1#
0"
b0 !
$end
#10
1%
#20
1(
b1 !
b1 &
1'
0%
1"
#30
1%
#40
1*
1)
0(
b10 !
b10 &
0'
0%
#50
1%
#60
1(
b11 !
b11 &
1'
0%
#70
1%
#80
1,
1+
0*
0)
0(
b100 !
b100 &
0'
0%
#90
1%
#100
1(
b101 !
b101 &
1'
0%
#110
1%
#120
1*
1)
0(
b110 !
b110 &
0'
0%
#130
1%
#140
1(
b111 !
b111 &
1'
0%
#150
1%
#160
1-
0,
0+
0*
0)
0(
b1000 !
b1000 &
0'
0%
#170
1%
#180
1(
b1001 !
b1001 &
1'
0%
#190
1%
#200
1*
1)
0(
b1010 !
b1010 &
0'
0%
#210
1%
#220
1(
b1011 !
b1011 &
1'
0%
#230
1%
#240
1,
1+
0*
0)
0(
b1100 !
b1100 &
0'
0%
#250
1%
#260
1(
b1101 !
b1101 &
1'
0%
#270
1%
#280
1*
1)
0(
b1110 !
b1110 &
0'
0%
#290
1%
#300
1(
b1111 !
b1111 &
1'
0%
#310
1%
#320
0-
0,
0+
0*
0)
0(
b0 !
b0 &
0'
0%
